py3Dmol/__init__.py
py3dmol-2.5.2.dist-info/licenses/LICENSE.txt
py3dmol-2.5.2.dist-info/METADATA
py3dmol-2.5.2.dist-info/WHEEL
py3dmol-2.5.2.dist-info/top_level.txt
py3dmol-2.5.2.dist-info/RECORD
