Metadata-Version: 2.4
Name: py3Dmol
Version: 2.5.2
Summary: An IPython interface for embedding 3Dmol.js views in Jupyter notebooks
Home-page: https://3dmol.org
Author: David Koes
Author-email: dkoes@pitt.edu
License: MIT
Keywords: molecule protein visualization
Classifier: Development Status :: 5 - Production/Stable
Classifier: Intended Audience :: Developers
Classifier: Intended Audience :: Science/Research
Classifier: Topic :: Scientific/Engineering :: Chemistry
Classifier: Topic :: Scientific/Engineering :: Visualization
Classifier: Topic :: Scientific/Engineering :: Bio-Informatics
Classifier: License :: OSI Approved :: MIT License
Classifier: Programming Language :: Python :: 2
Classifier: Programming Language :: Python :: 3
License-File: LICENSE.txt
Provides-Extra: ipython
Requires-Dist: IPython; extra == "ipython"
Dynamic: author
Dynamic: author-email
Dynamic: classifier
Dynamic: description
Dynamic: home-page
Dynamic: keywords
Dynamic: license
Dynamic: license-file
Dynamic: provides-extra
Dynamic: summary
